{
  "UOAlive": {
    "Blacksmith": {
      "item_keys": {
        "mace": {
          "name": "Mace",
          "item_id": 3932,
          "buttons": [
            121,
            22
          ],
          "default_material_key": "ingot_iron",
          "resources": []
        },
        "maul": {
          "name": "Maul",
          "item_id": 5179,
          "buttons": [
            121,
            42
          ],
          "default_material_key": "ingot_iron",
          "resources": []
        },
        "cutlass": {
          "name": "Cutlass",
          "item_id": 5185,
          "buttons": [
            61,
            62
          ],
          "default_material_key": "ingot_iron",
          "resources": []
        },
        "katana": {
          "name": "Katana",
          "item_id": 5119,
          "buttons": [
            61,
            102
          ],
          "default_material_key": "ingot_iron",
          "resources": []
        },
        "scimitar": {
          "name": "Scimitar",
          "item_id": 5046,
          "buttons": [
            61,
            162
          ],
          "default_material_key": "ingot_iron",
          "resources": []
        },
        "platemail gorget": {
          "name": "Platemail Gorget",
          "item_id": 5139,
          "buttons": [
            1,
            182
          ],
          "default_material_key": "ingot_iron",
          "resources": []
        },
        "platemail gloves": {
          "name": "Platemail Gloves",
          "item_id": 5140,
          "buttons": [
            1,
            162
          ],
          "default_material_key": "ingot_iron",
          "resources": []
        },
        "platemail arms": {
          "name": "Platemail Arms",
          "item_id": 5136,
          "buttons": [
            1,
            142
          ],
          "default_material_key": "ingot_iron",
          "resources": []
        },
        "platemail legs": {
          "name": "Platemail Legs",
          "item_id": 5137,
          "buttons": [
            1,
            202
          ],
          "default_material_key": "ingot_iron",
          "resources": []
        },
        "platemail tunic": {
          "name": "Platemail Tunic",
          "item_id": 5141,
          "buttons": [
            1,
            222
          ],
          "default_material_key": "ingot_iron",
          "resources": []
        },
        "large battle axe": {
          "name": "Large Battle Axe",
          "item_id": 3911,
          "buttons": [
            81,
            82
          ],
          "default_material_key": "ingot_iron",
          "resources": []
        },
        "heater shield": {
          "name": "Heater Shield",
          "item_id": 7030,
          "buttons": [
            41,
            42
          ],
          "default_material_key": "ingot_dull_copper",
          "resources": []
        },
        "executioner's axe": {
          "name": "Executioner's Axe",
          "item_id": 3909,
          "buttons": [
            81,
            62
          ],
          "default_material_key": "ingot_iron",
          "resources": []
        },
        "ringmail sleeves": {
          "name": "Ringmail Sleeves",
          "item_id": 5102,
          "buttons": [
            1,
            42
          ],
          "default_material_key": "ingot_iron",
          "resources": []
        },
        "two handed axe": {
          "name": "Two Handed Axe",
          "item_id": 0,
          "buttons": [
            81,
            102
          ],
          "default_material_key": "ingot_iron",
          "resources": []
        },
        "metal kite shield": {
          "name": "Metal Kite Shield",
          "item_id": 7028,
          "buttons": [
            41,
            82
          ],
          "default_material_key": "ingot_dull_copper",
          "resources": []
        }
      }
    },
    "Tailor": {
      "item_keys": {
        "short pants": {
          "name": "Short Pants",
          "item_id": 5422,
          "buttons": [
            41,
            382
          ],
          "default_material_key": "cloth",
          "resources": []
        },
        "fur capes": {
          "name": "Fur Capes",
          "item_id": 8970,
          "buttons": [
            41,
            202
          ],
          "default_material_key": "cloth",
          "resources": []
        },
        "cloaks": {
          "name": "Cloaks",
          "item_id": 5397,
          "buttons": [
            41,
            142
          ],
          "default_material_key": "cloth",
          "resources": []
        },
        "fur boots": {
          "name": "Fur Boots",
          "item_id": 8967,
          "buttons": [
            81,
            22
          ],
          "default_material_key": "cloth",
          "resources": []
        },
        "robes": {
          "name": "Robes",
          "item_id": 7939,
          "buttons": [
            41,
            162
          ],
          "default_material_key": "cloth",
          "resources": []
        },
        "kasas": {
          "name": "Kasas",
          "item_id": 10136,
          "buttons": [
            21,
            282
          ],
          "default_material_key": "cloth",
          "resources": []
        },
        "ninja tabi": {
          "name": "Ninja Tabi",
          "item_id": 10135,
          "buttons": [
            81,
            42
          ],
          "default_material_key": "cloth",
          "resources": []
        },
        "oil cloths": {
          "name": "Oil Cloths",
          "item_id": 5981,
          "buttons": [
            61,
            302
          ],
          "default_material_key": "cloth",
          "resources": []
        },
        "elven shirts brown": {
          "name": "Elven Shirts (Brown)",
          "item_id": 12661,
          "buttons": [
            41,
            522
          ],
          "default_material_key": "cloth",
          "resources": []
        },
        "studded hiro sodes": {
          "name": "Studded Hiro Sodes",
          "item_id": 10110,
          "buttons": [
            141,
            142
          ],
          "default_material_key": "leather",
          "resources": []
        }
      }
    },
    "Carpentry": {
      "item_keys": {
        "medium crates": {
          "name": "Medium Crates",
          "item_id": 3647,
          "buttons": [
            41,
            42
          ],
          "default_material_key": "board",
          "resources": []
        },
        "large crates": {
          "name": "Large Crates",
          "item_id": 3645,
          "buttons": [
            41,
            62
          ],
          "default_material_key": "board",
          "resources": []
        },
        "wooden shields": {
          "name": "Wooden Shields",
          "item_id": 7034,
          "buttons": [
            81,
            2
          ],
          "default_material_key": "board",
          "resources": []
        },
        "fukiyas": {
          "name": "Fukiyas",
          "item_id": 10154,
          "buttons": [
            61,
            82
          ],
          "default_material_key": "board",
          "resources": []
        },
        "quarter staves": {
          "name": "Quarter Staves",
          "item_id": 3721,
          "buttons": [
            61,
            22
          ],
          "default_material_key": "board",
          "resources": []
        },
        "gnarled staff": {
          "name": "Gnarled Staff",
          "item_id": 5112,
          "buttons": [
            61,
            42
          ],
          "default_material_key": "board",
          "resources": []
        },
        "black staff": {
          "name": "Black Staff",
          "item_id": 3568,
          "buttons": [
            61,
            302
          ],
          "default_material_key": "board",
          "resources": []
        },
        "wild staff": {
          "name": "Wild Staff",
          "item_id": 5108,
          "buttons": [
            61,
            122
          ],
          "default_material_key": "board",
          "resources": []
        }
      }
    },
    "Tinker": {
      "item_keys": {
        "scissors": {
          "name": "Scissors",
          "item_id": 3999,
          "buttons": [
            41,
            2
          ],
          "default_material_key": "ingot_iron",
          "resources": []
        },
        "gears": {
          "name": "Gears",
          "item_id": 4179,
          "buttons": [
            61,
            3
          ],
          "default_material_key": "ingot_iron",
          "resources": []
        },
        "rings": {
          "name": "Rings",
          "item_id": 4234,
          "buttons": [
            1,
            2
          ],
          "default_material_key": "ingot_iron",
          "resources": []
        },
        "spyglasses": {
          "name": "Spyglasses",
          "item_id": 5365,
          "buttons": [
            101,
            102
          ],
          "default_material_key": "ingot_iron",
          "resources": []
        },
        "brilliant amber bracelet": {
          "name": "Brilliant Amber Bracelet",
          "item_id": 4230,
          "buttons": [
            161,
            2
          ],
          "default_material_key": "ingot_iron",
          "resources": []
        },
        "clock frame": {
          "name": "Clock Frame",
          "item_id": 0,
          "buttons": [
            21,
            82
          ],
          "default_material_key": "boards",
          "resources": []
        }
      }
    }
  }
}